sphinx_timetravel/__init__.py
sphinx_timetravel/timeline.py
sphinx_timetravel/_static/timeline.css
sphinx_timetravel-0.2.0.dist-info/licenses/LICENSE
sphinx_timetravel-0.2.0.dist-info/METADATA
sphinx_timetravel-0.2.0.dist-info/WHEEL
sphinx_timetravel-0.2.0.dist-info/entry_points.txt
sphinx_timetravel-0.2.0.dist-info/top_level.txt
sphinx_timetravel-0.2.0.dist-info/RECORD
