Metadata-Version: 2.4
Name: sphinx-timetravel
Version: 0.2.0
Summary: Sphinx plugin for displaying interactive timelines with year/month resolution
Home-page: https://github.com/robbinespu/sphinx-timetravel
Author: Robbi Nespu
Author-email: Robbi Nespu <robbinespu@gmail.com>
License: MIT
Project-URL: Homepage, https://github.com/robbinespu/sphinx-timetravel
Project-URL: Documentation, https://github.com/robbinespu/sphinx-timetravel#readme
Project-URL: Source Code, https://github.com/robbinespu/sphinx-timetravel
Project-URL: Bug Tracker, https://github.com/robbinespu/sphinx-timetravel/issues
Keywords: sphinx,documentation,timeline,visualization
Classifier: Development Status :: 3 - Alpha
Classifier: Environment :: Plugins
Classifier: Intended Audience :: Developers
Classifier: License :: OSI Approved :: MIT License
Classifier: Natural Language :: English
Classifier: Operating System :: OS Independent
Classifier: Programming Language :: Python
Classifier: Programming Language :: Python :: 3
Classifier: Programming Language :: Python :: 3.7
Classifier: Programming Language :: Python :: 3.8
Classifier: Programming Language :: Python :: 3.9
Classifier: Programming Language :: Python :: 3.10
Classifier: Programming Language :: Python :: 3.11
Classifier: Programming Language :: Python :: 3.12
Classifier: Topic :: Documentation
Classifier: Framework :: Sphinx
Classifier: Framework :: Sphinx :: Extension
Requires-Python: >=3.7
License-File: LICENSE
Requires-Dist: Sphinx>=4.0
Provides-Extra: dev
Requires-Dist: pytest>=6.0; extra == "dev"
Requires-Dist: pytest-cov; extra == "dev"
Requires-Dist: sphinx-rtd-theme; extra == "dev"
Requires-Dist: twine>=3.0; extra == "dev"
Requires-Dist: build>=0.7; extra == "dev"
Dynamic: author
Dynamic: home-page
Dynamic: license-file
Dynamic: requires-python
